design.sv
// Code your design here
module serial_2_comp(comp_reg, num, load, rst, carry, clk);
  output reg[3:0]comp_reg;			//register for storing final result
  output reg carry;					//register for storing internal carry
  input [3:0]num;					
  input load, rst, clk;
  
  always@(posedge clk, negedge rst) begin	//asynchronous reset 
    if(!rst) begin
      comp_reg <= 4'b0000;
      carry <= 1'b1;
    end
    else if(load) begin						//loadind no to be complimented	
      comp_reg <= num;
    end
    else begin								//behavioural design
      case({comp_reg[0], carry})
        2'b00: begin
          comp_reg[3:0] <= {1'b1, comp_reg[3:1]};
          carry <= 1'b0;
        end
        2'b01: begin
          comp_reg[3:0] <= {1'b0, comp_reg[3:1]};
          carry <= 1'b1;
        end
        2'b10: begin
          comp_reg[3:0] <= {1'b0, comp_reg[3:1]};
          carry <= 1'b0;
        end
        2'b11: begin
          comp_reg[3:0] <= {1'b1, comp_reg[3:1]};
          carry <= 1'b0;
        end
      endcase
    end
  end
endmodule

testbench.sv
// Code your testbench here
// or browse Examples
module t_serial_2_comp;
  wire [3:0]comp_reg;
  wire carry;
  reg clk, load, rst;
  reg [3:0]num;
  
  
  serial_2_comp M_UUT(comp_reg, num, load, rst, carry, clk);
  
  always
    #5 clk = !clk;
  initial
    begin
      $dumpfile("comp.vcd");
      $dumpvars(0, t_serial_2_comp);
      $monitor($time, " load= %b | rst= %b | num= %b || carry= %b || cmpl=%b",
               load, rst, num, carry, comp_reg);
      rst = 1'b0; load = 1'b0; num = 4'b0000; clk = 1'b0;
      #2 rst = 1'b1; load = 1'b1;num = 4'b0001;
      #8 load=1'b0;
      #42 $finish;
    end
endmodule

comp.vcd
$date
	Fri Aug 14 07:21:33 2020
$end
$version
	Icarus Verilog
$end
$timescale
	1s
$end
$scope module t_serial_2_comp $end
$var wire 1 ! carry $end
$var wire 4 " comp_reg [3:0] $end
$var reg 1 # clk $end
$var reg 1 $ load $end
$var reg 4 % num [3:0] $end
$var reg 1 & rst $end
$scope module M_UUT $end
$var wire 1 ' clk $end
$var wire 1 ( load $end
$var wire 4 ) num [3:0] $end
$var wire 1 * rst $end
$var reg 1 + carry $end
$var reg 4 , comp_reg [3:0] $end
$upscope $end
$upscope $end
$enddefinitions $end
#0
$dumpvars
b0 ,
1+
0*
b0 )
0(
0'
0&
b0 %
0$
0#
b0 "
1!
$end
#2
b1 %
b1 )
1$
1(
1&
1*
#5
b1 ,
b1 "
1#
1'
#10
0#
0'
0$
0(
#15
0+
0!
b1000 ,
b1000 "
1#
1'
#20
0#
0'
#25
b1100 ,
b1100 "
1#
1'
#30
0#
0'
#35
b1110 ,
b1110 "
1#
1'
#40
0#
0'
#45
b1111 ,
b1111 "
1#
1'
